yawpg/__init__.py
yawpg/_defaults.py
yawpg/_host.py
yawpg/_pagetor.py
yawpg/_template_engine.py
yawpg/public/html/template.html
yawpg-0.1.0.dist-info/LICENSE
yawpg-0.1.0.dist-info/WHEEL
yawpg-0.1.0.dist-info/METADATA
yawpg-0.1.0.dist-info/RECORD
